discord_code_bot/__init__.py
discord_code_bot/discord_code_bot.py
discord_code_bot-0.1.2.dist-info/LICENSE
discord_code_bot-0.1.2.dist-info/METADATA
discord_code_bot-0.1.2.dist-info/WHEEL
discord_code_bot-0.1.2.dist-info/top_level.txt
discord_code_bot-0.1.2.dist-info/RECORD
